odoo10_addon_mrp_bom_matrix_report-10.0.1.0.0-py2.7-nspkg.pth
odoo/addons/mrp_bom_matrix_report/README.rst
odoo/addons/mrp_bom_matrix_report/__init__.py
odoo/addons/mrp_bom_matrix_report/__manifest__.py
odoo/addons/mrp_bom_matrix_report/models/__init__.py
odoo/addons/mrp_bom_matrix_report/models/mrp_bom_matrix_report.py
odoo/addons/mrp_bom_matrix_report/security/ir.model.access.csv
odoo/addons/mrp_bom_matrix_report/views/report_mrp_bom_matrix_view.xml
odoo10_addon_mrp_bom_matrix_report-10.0.1.0.0.dist-info/DESCRIPTION.rst
odoo10_addon_mrp_bom_matrix_report-10.0.1.0.0.dist-info/METADATA
odoo10_addon_mrp_bom_matrix_report-10.0.1.0.0.dist-info/RECORD
odoo10_addon_mrp_bom_matrix_report-10.0.1.0.0.dist-info/WHEEL
odoo10_addon_mrp_bom_matrix_report-10.0.1.0.0.dist-info/metadata.json
odoo10_addon_mrp_bom_matrix_report-10.0.1.0.0.dist-info/namespace_packages.txt
odoo10_addon_mrp_bom_matrix_report-10.0.1.0.0.dist-info/top_level.txt
